src/dff.v
module dff(
    input clk,
    input d,
    output reg q
);
always @(posedge clk)
begin
    q <= d;
end
endmodule

tb/dff_tb.v
`timescale 1ns/1ps

module dff_tb;
reg clk;
reg d;
wire q;
dff uut(
    .clk(clk),
    .d(d),
    .q(q)
);
always #5 clk = ~clk;
initial
begin
    clk = 0;
    d = 0;
    $dumpfile("waveforms/dff.vcd");
    $dumpvars(0,dff_tb);
    #10 d = 1;
    #10 d = 0;
    #10 d = 1;
    #10 d = 0;
    #20;
    $finish;
end
endmodule

waveforms/dff.vcd
$date
	Tue Jul 21 21:56:36 2026
$end
$version
	Icarus Verilog
$end
$timescale
	1ps
$end
$scope module dff_tb $end
$var wire 1 ! q $end
$var reg 1 " clk $end
$var reg 1 # d $end
$scope module uut $end
$var wire 1 " clk $end
$var wire 1 # d $end
$var reg 1 ! q $end
$upscope $end
$upscope $end
$enddefinitions $end
#0
$dumpvars
0#
0"
x!
$end
#5000
0!
1"
#10000
0"
1#
#15000
1!
1"
#20000
0"
0#
#25000
0!
1"
#30000
0"
1#
#35000
1!
1"
#40000
0"
0#
#45000
0!
1"
