src/down_counter.v
module down_counter(
    input clk,
    input reset,
    output reg [3:0] count
);
always @(posedge clk)
begin
    if (reset)
        count <= 4'b1111;   
    else
        count <= count - 1;
end
endmodule

tb/down_counter_tb.v
`timescale 1ns/1ps

module down_counter_tb;
reg clk;
reg reset;
wire [3:0] count;
down_counter uut (
    .clk(clk),
    .reset(reset),
    .count(count)
);
always #5 clk = ~clk;
initial
begin
    clk = 0;
    reset = 1;
    $dumpfile("waveforms/down_counter.vcd");
    $dumpvars(0, down_counter_tb);
    #10 reset = 0;
    #100;
    $finish;
end
endmodule

waveforms/down_counter.vcd
$date
	Tue Jul 21 22:27:12 2026
$end
$version
	Icarus Verilog
$end
$timescale
	1ps
$end
$scope module down_counter_tb $end
$var wire 4 ! count [3:0] $end
$var reg 1 " clk $end
$var reg 1 # reset $end
$scope module uut $end
$var wire 1 " clk $end
$var wire 1 # reset $end
$var reg 4 $ count [3:0] $end
$upscope $end
$upscope $end
$enddefinitions $end
#0
$dumpvars
bx $
1#
0"
bx !
$end
#5000
b1111 !
b1111 $
1"
#10000
0"
0#
#15000
b1110 !
b1110 $
1"
#20000
0"
#25000
b1101 !
b1101 $
1"
#30000
0"
#35000
b1100 !
b1100 $
1"
#40000
0"
#45000
b1011 !
b1011 $
1"
#50000
0"
#55000
b1010 !
b1010 $
1"
#60000
0"
#65000
b1001 !
b1001 $
1"
#70000
0"
#75000
b1000 !
b1000 $
1"
#80000
0"
#85000
b111 !
b111 $
1"
#90000
0"
#95000
b110 !
b110 $
1"
#100000
0"
#105000
b101 !
b101 $
1"
