src/jkff.v
module jkff(
    input clk,
    input j,
    input k,
    output reg q
);
always @(posedge clk)
begin
    case ({j,k})
        2'b00: q <= q;   
        2'b01: q <= 0;   
        2'b10: q <= 1;   
        2'b11: q <= ~q;  
    endcase
end
endmodule

tb/jkff_tb.v
`timescale 1ns/1ps

module jkff_tb;
reg clk;
reg j;
reg k;
wire q;
jkff uut (
    .clk(clk),
    .j(j),
    .k(k),
    .q(q)
);
always #5 clk = ~clk;
initial
begin
    clk = 0;
    j = 0;
    k = 0;
    $dumpfile("waveforms/jkff.vcd");
    $dumpvars(0, jkff_tb);
    #10 j = 0; k = 0;   
    #10 j = 0; k = 1;   
    #10 j = 1; k = 0;   
    #10 j = 1; k = 1;   
    #20;
    $finish;
end
endmodule

waveforms/jkff.vcd
$date
	Tue Jul 21 22:08:31 2026
$end
$version
	Icarus Verilog
$end
$timescale
	1ps
$end
$scope module jkff_tb $end
$var wire 1 ! q $end
$var reg 1 " clk $end
$var reg 1 # j $end
$var reg 1 $ k $end
$scope module uut $end
$var wire 1 " clk $end
$var wire 1 # j $end
$var wire 1 $ k $end
$var reg 1 ! q $end
$upscope $end
$upscope $end
$enddefinitions $end
#0
$dumpvars
0$
0#
0"
x!
$end
#5000
1"
#10000
0"
#15000
1"
#20000
0"
1$
#25000
0!
1"
#30000
0"
0$
1#
#35000
1!
1"
#40000
0"
1$
#45000
0!
1"
#50000
0"
#55000
1!
1"
