src/register.v
module register(
    input clk,
    input reset,
    input [3:0] d,
    output reg [3:0] q
);
always @(posedge clk)
begin
    if (reset)
        q <= 4'b0000;
    else
        q <= d;
end
endmodule

tb/register_tb.v
`timescale 1ns/1ps

module register_tb;

reg clk;
reg reset;
reg [3:0] d;
wire [3:0] q;

register uut (
    .clk(clk),
    .reset(reset),
    .d(d),
    .q(q)
);

always #5 clk = ~clk;
initial
begin
    clk = 0;
    reset = 1;
    d = 4'b0000;
    $dumpfile("waveforms/register.vcd");
    $dumpvars(0, register_tb);
    #10 reset = 0;
    #10 d = 4'b1010;
    #10 d = 4'b1100;
    #10 d = 4'b1111;
    #10 d = 4'b0011;
    #20;
    $finish;
end
endmodule

waveforms/register.vcd
$date
	Tue Jul 21 22:13:43 2026
$end
$version
	Icarus Verilog
$end
$timescale
	1ps
$end
$scope module register_tb $end
$var wire 4 ! q [3:0] $end
$var reg 1 " clk $end
$var reg 4 # d [3:0] $end
$var reg 1 $ reset $end
$scope module uut $end
$var wire 1 " clk $end
$var wire 4 % d [3:0] $end
$var wire 1 $ reset $end
$var reg 4 & q [3:0] $end
$upscope $end
$upscope $end
$enddefinitions $end
#0
$dumpvars
bx &
b0 %
1$
b0 #
0"
bx !
$end
#5000
b0 !
b0 &
1"
#10000
0"
0$
#15000
1"
#20000
0"
b1010 #
b1010 %
#25000
b1010 !
b1010 &
1"
#30000
0"
b1100 #
b1100 %
#35000
b1100 !
b1100 &
1"
#40000
0"
b1111 #
b1111 %
#45000
b1111 !
b1111 &
1"
#50000
0"
b11 #
b11 %
#55000
b11 !
b11 &
1"
