src/up_counter.v
module up_counter(
    input clk,
    input reset,
    output reg [3:0] count
);
always @(posedge clk)
begin
    if (reset)
        count <= 4'b0000;
    else
        count <= count + 1;
end
endmodule

tb/up_counter_tb.v
`timescale 1ns/1ps

module up_counter_tb;
reg clk;
reg reset;
wire [3:0] count;
up_counter uut(
    .clk(clk),
    .reset(reset),
    .count(count)
);

always #5 clk = ~clk;
initial
begin
    clk = 0;
    reset = 1;
    $dumpfile("waveforms/up_counter.vcd");
    $dumpvars(0, up_counter_tb);
    #10 reset = 0;
    #100;
    $finish;
end
endmodule

waveforms/up_counter.vcd
$date
	Tue Jul 21 22:19:42 2026
$end
$version
	Icarus Verilog
$end
$timescale
	1ps
$end
$scope module up_counter_tb $end
$var wire 4 ! count [3:0] $end
$var reg 1 " clk $end
$var reg 1 # reset $end
$scope module uut $end
$var wire 1 " clk $end
$var wire 1 # reset $end
$var reg 4 $ count [3:0] $end
$upscope $end
$upscope $end
$enddefinitions $end
#0
$dumpvars
bx $
1#
0"
bx !
$end
#5000
b0 !
b0 $
1"
#10000
0"
0#
#15000
b1 !
b1 $
1"
#20000
0"
#25000
b10 !
b10 $
1"
#30000
0"
#35000
b11 !
b11 $
1"
#40000
0"
#45000
b100 !
b100 $
1"
#50000
0"
#55000
b101 !
b101 $
1"
#60000
0"
#65000
b110 !
b110 $
1"
#70000
0"
#75000
b111 !
b111 $
1"
#80000
0"
#85000
b1000 !
b1000 $
1"
#90000
0"
#95000
b1001 !
b1001 $
1"
#100000
0"
#105000
b1010 !
b1010 $
1"
